python_packaging_ch/__init__.py
python_packaging_ch/maths.py
python_packaging_ch-0.1.4.dist-info/LICENSE
python_packaging_ch-0.1.4.dist-info/METADATA
python_packaging_ch-0.1.4.dist-info/WHEEL
python_packaging_ch-0.1.4.dist-info/entry_points.txt
python_packaging_ch-0.1.4.dist-info/top_level.txt
python_packaging_ch-0.1.4.dist-info/RECORD
